{
    "id": "org.kde.kalzium",
    "branch": "master",
    "runtime": "org.kde.Platform",
    "runtime-version": "5.15",
    "sdk": "org.kde.Sdk",
    "command": "kalzium",
    "rename-icon": "kalzium",
    "tags": ["nightly"],
    "desktop-file-name-suffix": " (Nightly)",
    "finish-args": [
        "--device=dri",
        "--share=ipc",
        "--socket=x11",
        "--socket=wayland"
    ],
    "modules": [
        {
            "name": "kalzium",
            "buildsystem": "cmake-ninja",
            "sources": [ { "type": "git", "url": "https://invent.kde.org/kde/kalzium.git" } ]
        }
    ]
}
